MANIFEST.in
setup.py
improse/__init__.py
improse/improse
improse.egg-info/.DS_Store
improse.egg-info/PKG-INFO
improse.egg-info/SOURCES.txt
improse.egg-info/dependency_links.txt
improse.egg-info/requires.txt
improse.egg-info/top_level.txt
improse/data/original_data.csv
improse/data/smote5k_data.csv
improse/data/train_data.csv