Metadata-Version: 1.1
Name: improse
Version: 1.1
Summary: Integrated Methods for Prediction of Super-Enhancers
Home-page: https://github.com/asntech/improse
Author: Aziz Khan
Author-email: khana10@mails.tsinghua.edu.cn
License: UNKNOWN
Platform: UNKNOWN
Classifier: Intended Audience :: Developers
Classifier: Intended Audience :: Science/Research
Classifier: License :: OSI Approved :: MIT License
Classifier: Operating System :: OS Independent
Classifier: Programming Language :: Python :: 2.7
Classifier: Topic :: Scientific/Engineering :: Bio-Informatics
